{
  "name": "aws",
  "title": "AWS",
  "version": "1.0.0",
  "description": "Manage AWS cloud infrastructure: EC2, S3, Lambda, IAM, CloudWatch, ECS, Route53, SQS, SNS, and RDS via the AWS REST API.",
  "logo": "<svg viewBox=\\\"0 0 24 24\\\" xmlns=\\\"http://www.w3.org/2000/svg\\\"><path d=\\\"M6 19a5 5 0 0 1-1-9.9A6 6 0 0 1 17 8a4.5 4.5 0 0 1 3 8.5 1 1 0 0 1-.3.2A5 5 0 0 1 18 19H6Z\\\"/></svg>",
  "categories": [
    "Cloud Infrastructure"
  ],
  "keywords": [],
  "author": {
    "name": "OfficeOS Team",
    "url": "https://officeos.co"
  },
  "license": "MIT",
  "repository": "https://github.com/officeos-co/skill-aws",
  "contributors": [
    {
      "name": "Harro Krog",
      "url": "https://github.com/HarKro753"
    }
  ],
  "credentials": {
    "access_key_id": {
      "label": "Access Key ID",
      "kind": "text",
      "placeholder": "AKIA...",
      "help": "AWS Access Key ID from IAM. Create one at https://console.aws.amazon.com/iam/."
    },
    "secret_access_key": {
      "label": "Secret Access Key",
      "kind": "password",
      "placeholder": "wJalr...",
      "help": "AWS Secret Access Key paired with the Access Key ID."
    },
    "region": {
      "label": "Default Region",
      "kind": "text",
      "placeholder": "us-east-1",
      "help": "Default AWS region. Can be overridden per action with --region."
    }
  }
}
